[
  {
    "001": "https://bit.ly/quo(001)",
    "002": "https://bit.ly/quot(002)",
    "003": "https://bit.ly/quot(003)",
    "004": "https://bit.ly/quot(004)",
    "005": "https://bit.ly/quot(005)",
    "006": "https://bit.ly/quot(006)",
    "007": "https://bit.ly/quot(007)",
    "008": "https://bit.ly/quot(008)",
    "009": "https://bit.ly/quot(009)",
    "010": "https://bit.ly/quot(010)",
    "011": "https://bit.ly/quot(011)",
    "012": "https://bit.ly/quot(012)",
    "013": "https://bit.ly/quot(013)",
    "014": "https://bit.ly/quot(014)",
    "015": "https://bit.ly/quot(015)",
    "016": "https://bit.ly/quot(016)",
    "017": "https://bit.ly/quot(017)",
    "018": "https://bit.ly/quot(018)",
    "019": "https://bit.ly/quot(019)",
    "020": "https://bit.ly/quot(020)",
    "021": "https://bit.ly/quot(021)",
    "022": "https://bit.ly/quot(022)",
    "023": "https://bit.ly/quot(023)",
    "024": "https://bit.ly/quot(024)",
    "025": "https://bit.ly/quot(025)",
    "026": "https://bit.ly/quot(026)",
    "027": "https://bit.ly/quot(027)",
    "028": "https://bit.ly/quot(028)",
    "029": "https://bit.ly/quot(029)",
    "030": "https://bit.ly/quot(030)",
    "031": "https://bit.ly/quot(031)",
    "032": "https://bit.ly/quot(032)",
    "033": "https://bit.ly/quot(033)",
    "034": "https://bit.ly/quot(034)",
    "035": "https://bit.ly/quot(035)",
    "036": "https://bit.ly/quot(036)",
    "037": "https://bit.ly/quot(037)",
    "038": "https://bit.ly/quot(038)",
    "039": "https://bit.ly/quot(039)",
    "040": "https://bit.ly/quot(040)",
    "041": "https://bit.ly/quot(041)",
    "042": "https://bit.ly/quot(042)",
    "043": "https://bit.ly/quot(043)",
    "044": "https://bit.ly/quot(044)",
    "045": "https://bit.ly/quot(045)",
    "046": "https://bit.ly/quot(046)",
    "047": "https://bit.ly/quot(047)",
    "048": "https://bit.ly/quot(048)",
    "049": "https://bit.ly/quot(049)",
    "050": "https://bit.ly/quot(050)",
    "051": "https://bit.ly/quot(051)",
    "052": "https://bit.ly/quot(052)",
    "053": "https://bit.ly/quot(053)",
    "054": "https://bit.ly/quot(054)",
    "055": "https://bit.ly/quot(055)",
    "056": "https://bit.ly/quot(056)",
    "057": "https://bit.ly/quot(057)",
    "058": "https://bit.ly/quot(058)",
    "059": "https://bit.ly/quot(059)",
    "060": "https://bit.ly/quot(060)",
    "061": "https://bit.ly/quot(061)",
    "062": "https://bit.ly/quot(062)",
    "063": "https://bit.ly/quot(063)",
    "064": "https://bit.ly/quot(064)",
    "065": "https://bit.ly/quot(065)",
    "066": "https://bit.ly/quot(066)",
    "067": "https://bit.ly/quot(067)",
    "068": "https://bit.ly/quot(068)",
    "069": "https://bit.ly/quot(069)",
    "070": "https://bit.ly/quot(070)",
    "071": "https://bit.ly/quot(071)",
    "072": "https://bit.ly/quot(072)",
    "073": "https://bit.ly/quot(073)",
    "074": "https://bit.ly/quot(074)",
    "075": "https://bit.ly/quot(075)",
    "076": "https://bit.ly/quot(076)",
    "077": "https://bit.ly/quot(077)",
    "078": "https://bit.ly/quot(078)",
    "079": "https://bit.ly/quot(079)",
    "080": "https://bit.ly/quot(080)",
    "081": "https://bit.ly/quot(081)",
    "082": "https://bit.ly/quot(082)",
    "083": "https://bit.ly/quot(083)",
    "084": "https://bit.ly/quot(084)",
    "085": "https://bit.ly/quot(085)",
    "086": "https://bit.ly/quot(086)",
    "087": "https://bit.ly/quot(087)",
    "088": "https://bit.ly/quot(088)",
    "089": "https://bit.ly/quot(089)",
    "090": "https://bit.ly/quot(090)",
    "091": "https://bit.ly/quot(091)",
    "092": "https://bit.ly/quot(092)",
    "093": "https://bit.ly/quot(093)",
    "094": "https://bit.ly/quot(094)",
    "095": "https://bit.ly/quot(095)",
    "096": "https://bit.ly/quot(096)",
    "097": "https://bit.ly/quot(097)",
    "098": "https://bit.ly/quot(098)",
    "099": "https://bit.ly/quot(099)",
    "100": "https://bit.ly/quot(100)",
    "101": "https://bit.ly/quot(101)",
    "102": "https://bit.ly/quot(102)",
    "103": "https://bit.ly/quot(103)",
    "104": "https://bit.ly/quot(104)",
    "105": "https://bit.ly/quot(105)",
    "106": "https://bit.ly/quot(106)",
    "107": "https://bit.ly/quot(107)",
    "108": "https://bit.ly/quot(108)",
    "109": "https://bit.ly/quot(109)",
    "110": "https://bit.ly/quot(110)",
    "111": "https://bit.ly/quot(111)",
    "112": "https://bit.ly/quot(112)",
    "113": "https://bit.ly/quot(113)",
    "114": "https://bit.ly/quot(114)",
    "115": "https://bit.ly/quot(115)",
    "116": "https://bit.ly/quot(116)",
    "117": "https://bit.ly/quot(117)",
    "118": "https://bit.ly/quot(118)",
    "119": "https://bit.ly/quot(119)",
    "120": "https://bit.ly/quot(120)",
    "121": "https://bit.ly/quot(121)",
    "122": "https://bit.ly/quot(122)",
    "123": "https://bit.ly/quot(123)",
    "124": "https://bit.ly/quot(124)",
    "125": "https://bit.ly/quot(125)",
    "126": "https://bit.ly/quot(126)",
    "127": "https://bit.ly/quot(127)",
    "128": "https://bit.ly/quot(128)",
    "129": "https://bit.ly/quot(129)",
    "130": "https://bit.ly/quot(130)",
    "131": "https://bit.ly/quot(131)",
    "132": "https://bit.ly/quot(132)",
    "133": "https://bit.ly/quot(133)",
    "134": "https://bit.ly/quot(134)",
    "135": "https://bit.ly/quot(135)",
    "136": "https://bit.ly/quot(136)",
    "137": "https://bit.ly/quot(137)",
    "138": "https://bit.ly/quot(138)",
    "139": "https://bit.ly/quot(139)",
    "140": "https://bit.ly/quot(140)",
    "141": "https://bit.ly/quot(141)",
    "142": "https://bit.ly/quot(142)",
    "143": "https://bit.ly/quot(143)",
    "144": "https://bit.ly/quot(144)",
    "145": "https://bit.ly/quot(145)",
    "146": "https://bit.ly/quot(146)",
    "147": "https://bit.ly/quot(147)",
    "148": "https://bit.ly/quot(148)",
    "149": "https://bit.ly/quot(149)",
    "150": "https://bit.ly/quot(150)",
    "151": "https://bit.ly/quot(151)",
    "152": "https://bit.ly/quot(152)",
    "153": "https://bit.ly/quot(153)",
    "154": "https://bit.ly/quot(154)",
    "155": "https://bit.ly/quot(155)",
    "156": "https://bit.ly/quot(156)",
    "157": "https://bit.ly/quot(157)",
    "158": "https://bit.ly/quot(158)",
    "159": "https://bit.ly/quot(159)",
    "160": "https://bit.ly/quot(160)",
    "161": "https://bit.ly/quot(161)",
    "162": "https://bit.ly/quot(162)",
    "163": "https://bit.ly/quot(163)",
    "164": "https://bit.ly/quot(164)",
    "165": "https://bit.ly/quot(165)",
    "166": "https://bit.ly/quot(166)",
    "167": "https://bit.ly/quot(167)",
    "168": "https://bit.ly/quot(168)",
    "169": "https://bit.ly/quot(169)",
    "170": "https://bit.ly/quot(170)",
    "171": "https://bit.ly/quot(171)",
    "172": "https://bit.ly/quot(172)",
    "173": "https://bit.ly/quot(173)",
    "174": "https://bit.ly/quot(174)",
    "175": "https://bit.ly/quot(175)",
    "176": "https://bit.ly/quot(176)",
    "177": "https://bit.ly/quot(177)",
    "178": "https://bit.ly/quot(178)",
    "179": "https://bit.ly/quot(179)",
    "180": "https://bit.ly/quot(180)",
    "181": "https://bit.ly/quot(181)",
    "182": "https://bit.ly/quot(182)",
    "183": "https://bit.ly/quot(183)",
    "184": "https://bit.ly/quot(184)",
    "185": "https://bit.ly/quot(185)",
    "186": "https://bit.ly/quot(186)",
    "187": "https://bit.ly/quot(187)",
    "188": "https://bit.ly/quot(188)",
    "189": "https://bit.ly/quot(189)",
    "190": "https://bit.ly/quot(190)",
    "191": "https://bit.ly/quot(191)",
    "192": "https://bit.ly/quot(192)",
    "193": "https://bit.ly/quot(193)",
    "194": "https://bit.ly/quot(194)",
    "195": "https://bit.ly/quot(195)",
    "196": "https://bit.ly/quot(196)",
    "197": "https://bit.ly/quot(197)",
    "198": "https://bit.ly/quot(198)",
    "199": "https://bit.ly/quot(199)",
    "200": "https://bit.ly/quot(200)",
    "201": "https://bit.ly/quot(201)",
    "202": "https://bit.ly/quot(202)",
    "203": "https://bit.ly/quot(203)",
    "204": "https://bit.ly/quot(204)",
    "205": "https://bit.ly/quot(205)",
    "206": "https://bit.ly/quot(206)",
    "207": "https://bit.ly/quot(207)",
    "208": "https://bit.ly/quot(208)",
    "209": "https://bit.ly/quot(209)",
    "210": "https://bit.ly/quot(210)",
    "211": "https://bit.ly/quot(211)",
    "212": "https://bit.ly/quot(212)",
    "213": "https://bit.ly/quot(213)",
    "214": "https://bit.ly/quot(214)",
    "215": "https://bit.ly/quot(215)",
    "216": "https://bit.ly/quot(216)",
    "217": "https://bit.ly/quot(217)",
    "218": "https://bit.ly/quot(218)",
    "219": "https://bit.ly/quot(219)",
    "220": "https://bit.ly/quot(220)",
    "221": "https://bit.ly/quot(221)",
    "222": "https://bit.ly/quot(222)",
    "223": "https://bit.ly/quot(223)",
    "224": "https://bit.ly/quot(224)",
    "225": "https://bit.ly/quot(225)",
    "226": "https://bit.ly/quot(226)",
    "227": "https://bit.ly/quot(227)",
    "228": "https://bit.ly/quot(228)",
    "229": "https://bit.ly/quot(229)",
    "230": "https://bit.ly/quot(230)",
    "231": "https://bit.ly/quot(231)",
    "232": "https://bit.ly/quot(232)",
    "233": "https://bit.ly/quot(233)",
    "234": "https://bit.ly/quot(234)",
    "235": "https://bit.ly/quot(235)",
    "236": "https://bit.ly/quot(236)",
    "237": "https://bit.ly/quot(237)",
    "238": "https://bit.ly/quot(238)",
    "239": "https://bit.ly/quot(239)",
    "240": "https://bit.ly/quot(240)",
    "241": "https://bit.ly/quot(241)",
    "242": "https://bit.ly/quot(242)",
    "243": "https://bit.ly/quot(243)",
    "244": "https://bit.ly/quot(244)",
    "245": "https://bit.ly/quot(245)",
    "246": "https://bit.ly/quot(246)",
    "247": "https://bit.ly/quot(247)",
    "248": "https://bit.ly/quot(248)",
    "249": "https://bit.ly/quot(249)",
    "250": "https://bit.ly/quot(250)",
    "251": "https://bit.ly/quot(251)",
    "252": "https://bit.ly/quot(252)",
    "253": "https://bit.ly/quot(253)",
    "254": "https://bit.ly/quot(254)",
    "255": "https://bit.ly/quot(255)",
    "256": "https://bit.ly/quot(256)",
    "257": "https://bit.ly/quot(257)",
    "258": "https://bit.ly/quot(258)",
    "259": "https://bit.ly/quot(259)",
    "260": "https://bit.ly/quot(260)",
    "261": "https://bit.ly/quot(261)",
    "262": "https://bit.ly/quot(262)",
    "263": "https://bit.ly/quot(263)",
    "264": "https://bit.ly/quot(264)",
    "265": "https://bit.ly/quot(265)",
    "266": "https://bit.ly/quot(266)",
    "267": "https://bit.ly/quot(267)",
    "268": "https://bit.ly/quot(268)",
    "269": "https://bit.ly/quot(269)",
    "270": "https://bit.ly/quot(270)",
    "271": "https://bit.ly/quot(271)",
    "272": "https://bit.ly/quot(272)",
    "273": "https://bit.ly/quot(273)",
    "274": "https://bit.ly/quot(274)",
    "275": "https://bit.ly/quot(275)",
    "276": "https://bit.ly/quot(276)",
    "277": "https://bit.ly/quot(277)",
    "278": "https://bit.ly/quot(278)",
    "279": "https://bit.ly/quot(279)",
    "280": "https://bit.ly/quot(280)",
    "281": "https://bit.ly/quot(281)",
    "282": "https://bit.ly/quot(282)",
    "283": "https://bit.ly/quot(283)",
    "284": "https://bit.ly/quot(284)",
    "285": "https://bit.ly/quot(285)",
    "286": "https://bit.ly/quot(286)",
    "287": "https://bit.ly/quot(287)",
    "288": "https://bit.ly/quot(288)",
    "289": "https://bit.ly/quot(289)",
    "290": "https://bit.ly/quot(290)",
    "291": "https://bit.ly/quot(291)",
    "292": "https://bit.ly/quot(292)",
    "293": "https://bit.ly/quot(293)",
    "294": "https://bit.ly/quot(294)",
    "295": "https://bit.ly/quot(295)",
    "296": "https://bit.ly/quot(296)",
    "297": "https://bit.ly/quot(297)",
    "298": "https://bit.ly/quot(298)",
    "299": "https://bit.ly/quot(299)",
    "300": "https://bit.ly/quot(300)",
    "301": "https://bit.ly/quot(301)",
    "302": "https://bit.ly/quot(302)",
    "303": "https://bit.ly/quot(303)",
    "304": "https://bit.ly/quot(304)",
    "305": "https://bit.ly/quot(305)",
    "306": "https://bit.ly/quot(306)",
    "307": "https://bit.ly/quot(307)",
    "308": "https://bit.ly/quot(308)",
    "309": "https://bit.ly/quot(309)",
    "310": "https://bit.ly/quot(310)",
    "311": "https://bit.ly/quot(311)",
    "312": "https://bit.ly/quot(312)",
    "313": "https://bit.ly/quot(313)",
    "314": "https://bit.ly/quot(314)",
    "315": "https://bit.ly/quot(315)",
    "316": "https://bit.ly/quot(316)",
    "317": "https://bit.ly/quot(317)",
    "318": "https://bit.ly/quot(318)",
    "319": "https://bit.ly/quot(319)",
    "320": "https://bit.ly/quot(320)",
    "321": "https://bit.ly/quot(321)",
    "322": "https://bit.ly/quot(322)",
    "323": "https://bit.ly/quot(323)",
    "324": "https://bit.ly/quot(324)",
    "325": "https://bit.ly/quot(325)",
    "326": "https://bit.ly/quot(326)",
    "327": "https://bit.ly/quot(327)",
    "328": "https://bit.ly/quot(328)",
    "329": "https://bit.ly/quot(329)",
    "330": "https://bit.ly/quot(330)",
    "331": "https://bit.ly/quot(331)",
    "332": "https://bit.ly/quot(332)",
    "333": "https://bit.ly/quot(333)",
    "334": "https://bit.ly/quot(334)",
    "335": "https://bit.ly/quot(335)",
    "336": "https://bit.ly/quot(336)",
    "337": "https://bit.ly/quot(337)",
    "338": "https://bit.ly/quot(338)",
    "339": "https://bit.ly/quot(339)",
    "340": "https://bit.ly/quot(340)",
    "341": "https://bit.ly/quot(341)",
    "342": "https://bit.ly/quot(342)",
    "343": "https://bit.ly/quot(343)",
    "344": "https://bit.ly/quot(344)",
    "345": "https://bit.ly/quot(345)",
    "346": "https://bit.ly/quot(346)",
    "347": "https://bit.ly/quot(347)",
    "348": "https://bit.ly/quot(348)",
    "349": "https://bit.ly/quot(349)",
    "350": "https://bit.ly/quot(350)",
    "351": "https://bit.ly/quot(351)",
    "352": "https://bit.ly/quot(352)",
    "353": "https://bit.ly/quot(353)",
    "354": "https://bit.ly/quot(354)",
    "355": "https://bit.ly/quot(355)",
    "356": "https://bit.ly/quot(356)",
    "357": "https://bit.ly/quot(357)",
    "358": "https://bit.ly/quot(358)",
    "359": "https://bit.ly/quot(359)",
    "360": "https://bit.ly/quot(360)",
    "361": "https://bit.ly/quot(361)",
    "362": "https://bit.ly/quot(362)",
    "363": "https://bit.ly/quot(363)",
    "364": "https://bit.ly/quot(364)",
    "365": "https://bit.ly/quot(365)",
    "366": "https://bit.ly/quot(366)",
    "367": "https://bit.ly/quot(367)",
    "368": "https://bit.ly/quot(368)",
    "369": "https://bit.ly/quot(369)",
    "370": "https://bit.ly/quot(370)",
    "371": "https://bit.ly/quot(371)",
    "372": "https://bit.ly/quot(372)",
    "373": "https://bit.ly/quot(373)",
    "374": "https://bit.ly/quot(374)",
    "375": "https://bit.ly/quot(375)",
    "376": "https://bit.ly/quot(376)",
    "377": "https://bit.ly/quot(377)",
    "378": "https://bit.ly/quot(378)",
    "379": "https://bit.ly/quot(379)",
    "380": "https://bit.ly/quot(380)",
    "381": "https://bit.ly/quot(381)",
    "382": "https://bit.ly/quot(382)",
    "383": "https://bit.ly/quot(383)",
    "384": "https://bit.ly/quot(384)",
    "385": "https://bit.ly/quot(385)",
    "386": "https://bit.ly/quot(386)",
    "387": "https://bit.ly/quot(387)",
    "388": "https://bit.ly/quot(388)",
    "389": "https://bit.ly/quot(389)",
    "390": "https://bit.ly/quot(390)",
    "391": "https://bit.ly/quot(391)",
    "392": "https://bit.ly/quot(392)",
    "393": "https://bit.ly/quot(393)",
    "394": "https://bit.ly/quot(394)",
    "395": "https://bit.ly/quot(395)",
    "396": "https://bit.ly/quot(396)",
    "397": "https://bit.ly/quot(397)",
    "398": "https://bit.ly/quot(398)",
    "399": "https://bit.ly/quot(399)",
    "400": "https://bit.ly/quot(400)",
    "401": "https://bit.ly/quot(401)",
    "402": "https://bit.ly/quot(402)",
    "403": "https://bit.ly/quot(403)",
    "404": "https://bit.ly/quot(404)",
    "405": "https://bit.ly/quot(405)",
    "406": "https://bit.ly/quot(406)",
    "407": "https://bit.ly/quot(407)",
    "408": "https://bit.ly/quot(408)",
    "409": "https://bit.ly/quot(409)",
    "410": "https://bit.ly/quot(410)",
    "411": "https://bit.ly/quot(411)",
    "412": "https://bit.ly/quot(412)",
    "413": "https://bit.ly/quot(413)",
    "414": "https://bit.ly/quot(414)",
    "415": "https://bit.ly/quot(415)",
    "416": "https://bit.ly/quot(416)",
    "417": "https://bit.ly/quot(417)",
    "418": "https://bit.ly/quot(418)",
    "419": "https://bit.ly/quot(419)",
    "420": "https://bit.ly/quot(420)",
    "421": "https://bit.ly/quot(421)",
    "422": "https://bit.ly/quot(422)",
    "423": "https://bit.ly/quot(423)"
  }
]
